pyindex/__init__.py
pyindex/test.py
pyindex/indexer/__init__.py
pyindex/indexer/indexer.py
pyindex/processor/__init__.py
pyindex/processor/flat_mapper.py
pyindex/processor/preprocessor.py
pyindex/processor/processor.py
pyindex/query/__init__.py
pyindex/query/query.py
pyindex-0.0.1.dist-info/LICENSE
pyindex-0.0.1.dist-info/METADATA
pyindex-0.0.1.dist-info/WHEEL
pyindex-0.0.1.dist-info/top_level.txt
pyindex-0.0.1.dist-info/RECORD
